{
	"ImportPath": "github.com/parkr/auto-reply",
	"GoVersion": "go1.8",
	"GodepVersion": "v79",
	"Packages": [
		"github.com/parkr/auto-reply/...",
		"github.com/stretchr/testify/assert"
	],
	"Deps": [
		{
			"ImportPath": "github.com/DataDog/datadog-go/statsd",
			"Comment": "1.0.0-7-g6ea09a7",
			"Rev": "6ea09a7540648568ce58b3d00eb1da133c2dcdd7"
		},
		{
			"ImportPath": "github.com/davecgh/go-spew/spew",
			"Comment": "v1.1.0",
			"Rev": "346938d642f2ec3594ed81d874461961cd0faa76"
		},
		{
			"ImportPath": "github.com/golang/groupcache/lru",
			"Rev": "72d04f9fcdec7d3821820cc4a6f150eae553639a"
		},
		{
			"ImportPath": "github.com/google/go-github/github",
			"Rev": "35d38108ba83757e9b6fc00e4ba7e2d597c651be"
		},
		{
			"ImportPath": "github.com/google/go-querystring/query",
			"Rev": "53e6ce116135b80d037921a7fdd5138cf32d7a8a"
		},
		{
			"ImportPath": "github.com/hashicorp/go-version",
			"Rev": "0181db47023708a38c2d20d2fe25a5fa034d5743"
		},
		{
			"ImportPath": "github.com/jekyll/dashboard",
			"Rev": "c0fdb07d5482c48f572ee3310cff6adb61b7dc13"
		},
		{
			"ImportPath": "github.com/jekyll/dashboard/triage",
			"Rev": "c0fdb07d5482c48f572ee3310cff6adb61b7dc13"
		},
		{
			"ImportPath": "github.com/parkr/changelog",
			"Rev": "cef0141074f9b8cc85a225bb4edca5278114e997"
		},
		{
			"ImportPath": "github.com/pmezard/go-difflib/difflib",
			"Comment": "v1.0.0",
			"Rev": "792786c7400a136282c1664665ae0a8db921c6c2"
		},
		{
			"ImportPath": "github.com/stretchr/testify/assert",
			"Comment": "v1.1.4-25-g2402e8e",
			"Rev": "2402e8e7a02fc811447d11f881aa9746cdc57983"
		},
		{
			"ImportPath": "golang.org/x/net/context",
			"Rev": "f5079bd7f6f74e23c4d65efa0f4ce14cbd6a3c0f"
		},
		{
			"ImportPath": "golang.org/x/net/context/ctxhttp",
			"Rev": "f5079bd7f6f74e23c4d65efa0f4ce14cbd6a3c0f"
		},
		{
			"ImportPath": "golang.org/x/oauth2",
			"Rev": "b53b38ad8a6435bd399ea76d0fa74f23149cca4e"
		},
		{
			"ImportPath": "golang.org/x/oauth2/internal",
			"Rev": "b53b38ad8a6435bd399ea76d0fa74f23149cca4e"
		},
		{
			"ImportPath": "golang.org/x/sync/errgroup",
			"Rev": "f52d1811a62927559de87708c8913c1650ce4f26"
		}
	]
}
